unifi_api/__init__.py
unifi_api/api.py
unifi_api/base_api.py
unifi_api/utils/__init__.py
unifi_api/utils/decorators.py
unifi_api/utils/exceptions.py
unifi_api/utils/models.py
mambo_unifi_api-1.0.5.dist-info/METADATA
mambo_unifi_api-1.0.5.dist-info/WHEEL
mambo_unifi_api-1.0.5.dist-info/top_level.txt
mambo_unifi_api-1.0.5.dist-info/RECORD
