Metadata-Version: 2.1
Name: mambo-unifi-api
Version: 1.0.5
Summary: UNKNOWN
Home-page: UNKNOWN
Author: Nelson Fonseca
Author-email: nelson.fonseca@mambowifi.com
License: UNKNOWN
Platform: UNKNOWN
Classifier: Development Status :: 3 - Alpha
Classifier: Intended Audience :: Information Technology
Classifier: Operating System :: OS Independent
Classifier: Programming Language :: Python :: 3
Classifier: Topic :: Software Development :: Libraries :: Python Modules
Classifier: Topic :: Utilities
Requires-Dist: requests (<3,>=2.21.0)
Requires-Dist: trafaret (>=1.2.0<1.3)
